{
  "skill": "powerloom-bds",
  "last_analyzed": "2026-06-13T13:52:36Z",
  "quality_score": 3,
  "assessment": "Completed task adequately by verifying cache and logging, but output is generic",
  "flags": [
    "generic_content"
  ],
  "avg_score": 3.57,
  "history": [
    {
      "date": "2026-06-12",
      "score": 3
    },
    {
      "date": "2026-06-12",
      "score": 3
    },
    {
      "date": "2026-06-12",
      "score": 3
    },
    {
      "date": "2026-06-12",
      "score": 3
    },
    {
      "date": "2026-06-12",
      "score": 3
    },
    {
      "date": "2026-06-12",
      "score": 3
    },
    {
      "date": "2026-06-12",
      "score": 5
    },
    {
      "date": "2026-06-12",
      "score": 3
    },
    {
      "date": "2026-06-12",
      "score": 3
    },
    {
      "date": "2026-06-12",
      "score": 5
    },
    {
      "date": "2026-06-12",
      "score": 4
    },
    {
      "date": "2026-06-12",
      "score": 3
    },
    {
      "date": "2026-06-13",
      "score": 3
    },
    {
      "date": "2026-06-13",
      "score": 5
    },
    {
      "date": "2026-06-13",
      "score": 3
    },
    {
      "date": "2026-06-13",
      "score": 4
    },
    {
      "date": "2026-06-13",
      "score": 4
    },
    {
      "date": "2026-06-13",
      "score": 3
    },
    {
      "date": "2026-06-13",
      "score": 4
    },
    {
      "date": "2026-06-13",
      "score": 3
    },
    {
      "date": "2026-06-13",
      "score": 3
    },
    {
      "date": "2026-06-13",
      "score": 4
    },
    {
      "date": "2026-06-13",
      "score": 4
    },
    {
      "date": "2026-06-13",
      "score": 3
    },
    {
      "date": "2026-06-13",
      "score": 4
    },
    {
      "date": "2026-06-13",
      "score": 5
    },
    {
      "date": "2026-06-13",
      "score": 3
    },
    {
      "date": "2026-06-13",
      "score": 5
    },
    {
      "date": "2026-06-13",
      "score": 3
    },
    {
      "date": "2026-06-13",
      "score": 3
    }
  ]
}
