{
  "skill": "powerloom-bds",
  "last_analyzed": "2026-06-10T20:12:25Z",
  "quality_score": 3,
  "assessment": "Completed basic task adequately but minimal output, just reading cache and logging",
  "flags": [
    "generic_content"
  ],
  "avg_score": 3.83,
  "history": [
    {
      "date": "2026-06-10",
      "score": 5
    },
    {
      "date": "2026-06-10",
      "score": 3
    },
    {
      "date": "2026-06-10",
      "score": 4
    },
    {
      "date": "2026-06-10",
      "score": 5
    },
    {
      "date": "2026-06-10",
      "score": 5
    },
    {
      "date": "2026-06-10",
      "score": 5
    },
    {
      "date": "2026-06-10",
      "score": 5
    },
    {
      "date": "2026-06-10",
      "score": 5
    },
    {
      "date": "2026-06-10",
      "score": 3
    },
    {
      "date": "2026-06-10",
      "score": 5
    },
    {
      "date": "2026-06-10",
      "score": 3
    },
    {
      "date": "2026-06-10",
      "score": 4
    },
    {
      "date": "2026-06-10",
      "score": 3
    },
    {
      "date": "2026-06-10",
      "score": 3
    },
    {
      "date": "2026-06-10",
      "score": 5
    },
    {
      "date": "2026-06-10",
      "score": 3
    },
    {
      "date": "2026-06-10",
      "score": 3
    },
    {
      "date": "2026-06-10",
      "score": 5
    },
    {
      "date": "2026-06-10",
      "score": 4
    },
    {
      "date": "2026-06-10",
      "score": 3
    },
    {
      "date": "2026-06-10",
      "score": 4
    },
    {
      "date": "2026-06-10",
      "score": 3
    },
    {
      "date": "2026-06-10",
      "score": 3
    },
    {
      "date": "2026-06-10",
      "score": 3
    },
    {
      "date": "2026-06-10",
      "score": 4
    },
    {
      "date": "2026-06-10",
      "score": 5
    },
    {
      "date": "2026-06-10",
      "score": 3
    },
    {
      "date": "2026-06-10",
      "score": 3
    },
    {
      "date": "2026-06-10",
      "score": 3
    },
    {
      "date": "2026-06-10",
      "score": 3
    }
  ]
}
