{
  "root": "card",
  "state": {},
  "elements": {
    "card": {
      "type": "Card",
      "props": {
        "title": "Whale Alert",
        "description": "WETH → USDC transaction"
      },
      "children": [
        "stack1"
      ]
    },
    "stack1": {
      "type": "Stack",
      "props": {
        "direction": "vertical",
        "gap": "md"
      },
      "children": [
        "heading1",
        "stack2",
        "separator1",
        "stack3"
      ]
    },
    "heading1": {
      "type": "Heading",
      "props": {
        "text": "🐋 Whale alert: WETH → USDC $1,037",
        "level": "h2"
      },
      "children": []
    },
    "stack2": {
      "type": "Stack",
      "props": {
        "direction": "vertical",
        "gap": "sm"
      },
      "children": [
        "text1",
        "text2",
        "text3",
        "text4"
      ]
    },
    "text1": {
      "type": "Text",
      "props": {
        "text": "Pool: 0xc7bBeC68d12a0d1830360F8Ec58fA599bA1b0e9b",
        "variant": "body"
      },
      "children": []
    },
    "text2": {
      "type": "Text",
      "props": {
        "text": "Epoch: 25144657",
        "variant": "body"
      },
      "children": []
    },
    "text3": {
      "type": "Text",
      "props": {
        "text": "Tx: 0x346c82002370ffa97d6a5ef8d41c4017197d92265a078855efb8def82127a4e4",
        "variant": "body"
      },
      "children": []
    },
    "text4": {
      "type": "Text",
      "props": {
        "text": "✅ Verified on-chain",
        "variant": "body"
      },
      "children": []
    },
    "separator1": {
      "type": "Separator",
      "props": {
        "orientation": "horizontal"
      },
      "children": []
    },
    "stack3": {
      "type": "Stack",
      "props": {
        "direction": "vertical",
        "gap": "sm"
      },
      "children": [
        "text5",
        "text6"
      ]
    },
    "text5": {
      "type": "Text",
      "props": {
        "text": "   cid: bafkreib3qx2lh4aac5paujartrm6epv4ydvrzuqxlx5daj3tf46vbas77q",
        "variant": "muted"
      },
      "children": []
    },
    "text6": {
      "type": "Text",
      "props": {
        "text": "   project: allTradesSnapshot:0x4198Bf81B55EE4Af6f9Ddc176F8021960813f641:mainnet-BDS_MAINNET_ALPHA_UNISWAPV3-ETH",
        "variant": "muted"
      },
      "children": []
    }
  }
}
