{
  "root": "card",
  "state": {},
  "elements": {
    "card": {
      "type": "Card",
      "props": {
        "title": "🐋 Powerloom BDS — Epochs 25195345–25195353 (9 epochs)"
      },
      "children": [
        "stack"
      ]
    },
    "stack": {
      "type": "Stack",
      "props": {
        "direction": "vertical",
        "gap": "md"
      },
      "children": [
        "heading",
        "top-trades-container",
        "active-wallets",
        "anomaly",
        "verification"
      ]
    },
    "heading": {
      "type": "Heading",
      "props": {
        "text": "Top trades:",
        "level": "h3"
      },
      "children": []
    },
    "top-trades-container": {
      "type": "Stack",
      "props": {
        "direction": "vertical",
        "gap": "sm"
      },
      "children": [
        "trade1",
        "trade2",
        "trade3",
        "trade4",
        "trade5",
        "trade6",
        "trade7"
      ]
    },
    "trade1": {
      "type": "Text",
      "props": {
        "text": "• $205.6K BUY RLUSD/USDC — 0xE592427A…861564 (block 25195348)",
        "variant": "body"
      },
      "children": []
    },
    "trade1-link": {
      "type": "Link",
      "props": {
        "label": "TX",
        "href": "https://etherscan.io/tx/0xf8410dfe1749ee92fa19498bf5fcbcfb3312d4e9e6ceff007ff80bea27ab1189"
      },
      "children": []
    },
    "trade2": {
      "type": "Text",
      "props": {
        "text": "• $86.4K BUY USDC/WETH — 0xBdb3ba9f…DF47B6 (block 25195349)",
        "variant": "body"
      },
      "children": []
    },
    "trade2-link": {
      "type": "Link",
      "props": {
        "label": "TX",
        "href": "https://etherscan.io/tx/0xe22a5dfcb64fb695f2785b24aa14e94f61de89673f1efdee128005f2ffba5be7"
      },
      "children": []
    },
    "trade3": {
      "type": "Text",
      "props": {
        "text": "• $72.5K BUY DAI/USDC — 0xE592427A…861564 (block 25195350)",
        "variant": "body"
      },
      "children": []
    },
    "trade3-link": {
      "type": "Link",
      "props": {
        "label": "TX",
        "href": "https://etherscan.io/tx/0x29f3bcd91df84609dc36689a8d423f176f22d8fa95b7dac05ef855967c637e8d"
      },
      "children": []
    },
    "trade4": {
      "type": "Text",
      "props": {
        "text": "• $48.9K BUY USDC/USDT — 0x63242A4E…CC6cB0 (block 25195346)",
        "variant": "body"
      },
      "children": []
    },
    "trade4-link": {
      "type": "Link",
      "props": {
        "label": "TX",
        "href": "https://etherscan.io/tx/0x7698035c9319e1e97a41977d8f235cbfd243a9f68b3b9e701e5d7d37d51d3cb3"
      },
      "children": []
    },
    "trade5": {
      "type": "Text",
      "props": {
        "text": "• $39.2K BUY USDC/USDT — 0x63242A4E…CC6cB0 (block 25195347)",
        "variant": "body"
      },
      "children": []
    },
    "trade5-link": {
      "type": "Link",
      "props": {
        "label": "TX",
        "href": "https://etherscan.io/tx/0xc5c07f89055b05460f507d1c3b33f45e808a2df8149d8bcacccddb0688753c4e"
      },
      "children": []
    },
    "trade6": {
      "type": "Text",
      "props": {
        "text": "• $24.0K BUY WBTC/XAUt — anon (block 25195348)",
        "variant": "body"
      },
      "children": []
    },
    "trade6-link": {
      "type": "Link",
      "props": {
        "label": "TX",
        "href": "https://etherscan.io/tx/0x0a7a776357bbfb6fb8dd2edadd566d41b0332daa907372f53d7109020c7f8493"
      },
      "children": []
    },
    "trade7": {
      "type": "Text",
      "props": {
        "text": "• $22.9K BUY USDC/WETH — anon (block 25195349)",
        "variant": "body"
      },
      "children": []
    },
    "trade7-link": {
      "type": "Link",
      "props": {
        "label": "TX",
        "href": "https://etherscan.io/tx/0x72662eae3bea538bb4369b6c186688ab2379f3a18121fb7dabc2c309a318df9a"
      },
      "children": []
    },
    "active-wallets": {
      "type": "Text",
      "props": {
        "text": "Active wallets: 0x51C72848 (8 trades), 0xBdb3ba9f (4), 0x63242A4E ($88K USDC/USDT), 0xE592427A (RLUSD+$DAI $278K), 0x278d858f (3 ZAMA oracle anomalies)",
        "variant": "body"
      },
      "children": []
    },
    "anomaly": {
      "type": "Alert",
      "props": {
        "title": "⚠️ ZAMA/USDT",
        "message": "3 oracle anomalies (displayed ~$10^39–$10^42, actual ~$289–$766 USDT)",
        "type": "warning"
      },
      "children": []
    },
    "verification": {
      "type": "Text",
      "props": {
        "text": "✅ Verified on-chain via Powerloom BDS",
        "variant": "muted"
      },
      "children": []
    }
  }
}
